cogssg/__init__.py
cogssg/__main__.py
cogssg/cogssg.py
cogssg-0.1.0.dist-info/METADATA
cogssg-0.1.0.dist-info/WHEEL
cogssg-0.1.0.dist-info/entry_points.txt
cogssg-0.1.0.dist-info/licenses/LICENSE
cogssg-0.1.0.dist-info/RECORD
