Metadata-Version: 2.4
Name: cogssg
Version: 0.1.0
Summary: A simple static site generator
Project-URL: Homepage, https://github.com/natanjunges/cogssg
Project-URL: Issues, https://github.com/natanjunges/cogssg/issues
Author-email: Natan Junges <natanajunges@gmail.com>
License-File: LICENSE
Classifier: License :: OSI Approved :: Apache Software License
Classifier: Operating System :: OS Independent
Classifier: Programming Language :: Python :: 3
Requires-Python: >=3.10
Requires-Dist: cogapp
